django_castle/__init__.py
django_castle/api.py
django_castle/models.py
django_castle/templatetags/__init__.py
django_castle/templatetags/castle.py
django_castle-0.1.1.dist-info/DESCRIPTION.rst
django_castle-0.1.1.dist-info/METADATA
django_castle-0.1.1.dist-info/metadata.json
django_castle-0.1.1.dist-info/pbr.json
django_castle-0.1.1.dist-info/RECORD
django_castle-0.1.1.dist-info/top_level.txt
django_castle-0.1.1.dist-info/WHEEL
