Metadata-Version: 2.0
Name: django-castle
Version: 0.1.1
Summary: A django integration for the castle.io service
Home-page: https://github.com/ulmus/django-castle
Author: Jens Alm
Author-email: jens.alm@prorenata.se
License: BSD
Keywords: django-castle
Platform: UNKNOWN
Classifier: Development Status :: 3 - Alpha
Classifier: Framework :: Django
Classifier: Intended Audience :: Developers
Classifier: License :: OSI Approved :: BSD License
Classifier: Natural Language :: English
Classifier: Programming Language :: Python :: 2
Classifier: Programming Language :: Python :: 2.7
Classifier: Programming Language :: Python :: 3
Classifier: Programming Language :: Python :: 3.3
Classifier: Programming Language :: Python :: 3.4
